mongohelper/__init__.py
mongohelper/operator/__init__.py
mongohelper/operator/collection.py
mongohelper/operator/dict.py
mongohelper/operator/list.py
mongohelper/operator/obj.py
mongo_pythonic-0.2.3.dist-info/LICENSE.txt
mongo_pythonic-0.2.3.dist-info/METADATA
mongo_pythonic-0.2.3.dist-info/WHEEL
mongo_pythonic-0.2.3.dist-info/top_level.txt
mongo_pythonic-0.2.3.dist-info/RECORD
