Metadata-Version: 2.2
Name: mongo_pythonic
Version: 0.2.3
Summary: Repackage pymongo to make it more pythonic
Home-page: https://github.com/guaixiao7720/mongohelper
Author: guai_xiao
Author-email: guai-xiao@hotmail.com
License: GPL-3.0
Classifier: Programming Language :: Python :: 3
Classifier: License :: OSI Approved :: GNU General Public License v3 (GPLv3)
Classifier: Operating System :: OS Independent
Requires-Python: >=3.6
License-File: LICENSE.txt
Requires-Dist: pymongo
Dynamic: author
Dynamic: author-email
Dynamic: classifier
Dynamic: description
Dynamic: description-content-type
Dynamic: home-page
Dynamic: license
Dynamic: requires-dist
Dynamic: requires-python
Dynamic: summary
